jexelapi/__init__.py
jexelapi/__main__.py
jexelapi/controllers/__init__.py
jexelapi/controllers/utilities.py
jexelapi/controllers/exceptions/__init__.py
jexelapi/controllers/exceptions/exceptions.py
jexelapi/controllers/init/__init__.py
jexelapi/controllers/init/data.py
jexelapi/controllers/init/init.py
jexelapi/controllers/init/layouts/__init__.py
jexelapi/controllers/init/layouts/core/__init__.py
jexelapi/controllers/init/layouts/core/app.py
jexelapi/controllers/init/layouts/core/auto_alembic.py
jexelapi/controllers/init/layouts/core/basic_controller.py
jexelapi/controllers/init/layouts/core/config.py
jexelapi/controllers/init/layouts/core/database.py
jexelapi/controllers/init/layouts/core/main.py
jexelapi/controllers/init/layouts/core/models.py
jexelapi/controllers/init/layouts/core/auth/__init__.py
jexelapi/controllers/init/layouts/core/auth/authentication.py
jexelapi/controllers/init/layouts/core/auth/base_auth.py
jexelapi/controllers/init/layouts/core/auth/db_model.py
jexelapi/controllers/init/layouts/core/auth/exceptions.py
jexelapi/controllers/init/layouts/core/auth/routes.py
jexelapi/controllers/init/layouts/core/auth/schemas.py
jexelapi/controllers/init/layouts/core/auth/controllers/__init__.py
jexelapi/controllers/init/layouts/core/auth/controllers/google.py
jexelapi/controllers/init/layouts/core/auth/controllers/users.py
jexelapi/controllers/init/layouts/core/debug/__init__.py
jexelapi/controllers/init/layouts/core/debug/controllers.py
jexelapi/controllers/init/layouts/core/debug/exceptions.py
jexelapi/controllers/init/layouts/core/debug/router.py
jexelapi/controllers/init/layouts/core/files/__init__.py
jexelapi/controllers/init/layouts/core/files/controllers.py
jexelapi/controllers/init/layouts/core/files/db_model.py
jexelapi/controllers/init/layouts/core/files/exceptions.py
jexelapi/controllers/init/layouts/core/files/router.py
jexelapi/controllers/init/layouts/core/migrations/__init__.py
jexelapi/controllers/init/layouts/core/migrations/env.py
jexelapi-1.0.12.dist-info/METADATA
jexelapi-1.0.12.dist-info/WHEEL
jexelapi-1.0.12.dist-info/top_level.txt
jexelapi-1.0.12.dist-info/RECORD
